aim/__init__.py
aim/__version__.py
aim/cli/__init__.py
aim/cli/deploy.py
aim/deploy/__init__.py
aim/deploy/docker.py
aim/deploy/docker_image.py
aim/deploy/generic.py
aim/deploy/docker/__init__.py
aim/deploy/docker/bla.py
aim/deploy/docker/build.py
aim/deploy/docker/configs.py
aim/deploy/docker/docker_ops_prep.py
aim/deploy/docker/server_prep.py
aim/deploy/docker/utils.py
aim/deploy/docker/_ops/Dockerfile.py
aim/deploy/docker/_ops/__init__.py
aim/deploy/docker/_ops/requirements.txt.py
aim/deploy/docker/_server_files/__init__.py
aim/deploy/docker/_server_files/app.py
aim/engine/__init__.py
aim/engine/aim_model.py
aim/engine/metadata.py
aim/engine/representation.py
aim/engine/deployables/__init__.py
aim/engine/deployables/configs.py
aim/engine/deployables/onnx_runtime.py
aim/export/__init__.py
aim/export/metadata.py
aim/export/pytorch.py
aim/export/utils.py
aim/export/wrapper.py
aim/origin/__init__.py
aim/origin/metadata.py
aim/origin/wrapper.py
aimhub-0.1.0.data/data/data/deploy/_ops/Dockerfile
aimhub-0.1.0.data/data/data/deploy/_ops/requirements.txt
aimhub-0.1.0.data/data/data/deploy/_server_files/app.py
aimhub-0.1.0.dist-info/LICENSE
aimhub-0.1.0.dist-info/METADATA
aimhub-0.1.0.dist-info/WHEEL
aimhub-0.1.0.dist-info/entry_points.txt
aimhub-0.1.0.dist-info/top_level.txt
aimhub-0.1.0.dist-info/RECORD
