Metadata-Version: 2.1
Name: aimhub
Version: 0.1.0
Summary: AI Deployment tool
Home-page: https://github.com/SGevorg/aim-deploy
Author: Gevorg Soghomonyan
Author-email: sgevorg@aimhub.io
License: MIT
Platform: UNKNOWN
Classifier: License :: OSI Approved :: MIT License
Classifier: Programming Language :: Python
Classifier: Programming Language :: Python :: 3
Classifier: Programming Language :: Python :: 3.7
Classifier: Programming Language :: Python :: Implementation :: CPython
Classifier: Programming Language :: Python :: Implementation :: PyPy
Requires-Python: >=3.6.0
Requires-Dist: click (>=6.7)
